nvitop/__init__.py
nvitop/__main__.py
nvitop/cli.py
nvitop/select.py
nvitop/version.py
nvitop/api/__init__.py
nvitop/api/caching.py
nvitop/api/collector.py
nvitop/api/device.py
nvitop/api/host.py
nvitop/api/libcuda.py
nvitop/api/libcudart.py
nvitop/api/libnvml.py
nvitop/api/process.py
nvitop/api/termcolor.py
nvitop/api/utils.py
nvitop/callbacks/__init__.py
nvitop/callbacks/keras.py
nvitop/callbacks/lightning.py
nvitop/callbacks/pytorch_lightning.py
nvitop/callbacks/tensorboard.py
nvitop/callbacks/utils.py
nvitop/tui/__init__.py
nvitop/tui/tui.py
nvitop/tui/library/__init__.py
nvitop/tui/library/device.py
nvitop/tui/library/displayable.py
nvitop/tui/library/history.py
nvitop/tui/library/host.py
nvitop/tui/library/keybinding.py
nvitop/tui/library/libcurses.py
nvitop/tui/library/messagebox.py
nvitop/tui/library/mouse.py
nvitop/tui/library/process.py
nvitop/tui/library/selection.py
nvitop/tui/library/utils.py
nvitop/tui/library/widestring.py
nvitop/tui/screens/__init__.py
nvitop/tui/screens/base.py
nvitop/tui/screens/environ.py
nvitop/tui/screens/help.py
nvitop/tui/screens/metrics.py
nvitop/tui/screens/treeview.py
nvitop/tui/screens/main/__init__.py
nvitop/tui/screens/main/panels/__init__.py
nvitop/tui/screens/main/panels/base.py
nvitop/tui/screens/main/panels/device.py
nvitop/tui/screens/main/panels/host.py
nvitop/tui/screens/main/panels/process.py
nvitop_musa-1.6.1.dist-info/COPYING
nvitop_musa-1.6.1.dist-info/LICENSE
nvitop_musa-1.6.1.dist-info/METADATA
nvitop_musa-1.6.1.dist-info/WHEEL
nvitop_musa-1.6.1.dist-info/entry_points.txt
nvitop_musa-1.6.1.dist-info/top_level.txt
nvitop_musa-1.6.1.dist-info/RECORD
